DAY3_Full_adder/FA.v
module FA(input a_in, b_in, c_in, output sum, carry);
  assign sum = a_in ^ b_in ^ c_in;
  assign carry = (a_in & b_in) | (b_in & c_in) | (a_in & c_in);
endmodule

DAY3_Full_adder/tb_FA.v

module tb_fa;

  // Declare test bench variables
  reg a_in, b_in, c_in;
  wire sum, carry;

  // Instantiate the full adder module
  FA uut (
    .a_in(a_in), 
    .b_in(b_in), 
    .c_in(c_in), 
    .sum(sum), 
    .carry(carry)
  );

  // Apply stimulus
  initial begin
    a_in = 1'b0; b_in = 1'b0; c_in = 1'b0; #10;
    a_in = 1'b0; b_in = 1'b0; c_in = 1'b1; #10;
    a_in = 1'b0; b_in = 1'b1; c_in = 1'b0; #10;
    a_in = 1'b0; b_in = 1'b1; c_in = 1'b1; #10;
    a_in = 1'b1; b_in = 1'b0; c_in = 1'b0; #10;
    a_in = 1'b1; b_in = 1'b0; c_in = 1'b1; #10;
    a_in = 1'b1; b_in = 1'b1; c_in = 1'b0; #10;
    a_in = 1'b1; b_in = 1'b1; c_in = 1'b1; #10;
  end

  // Finish simulation after 100 time units
  initial begin
    #100 $finish;
  end

  // Dump waveforms for viewing
  initial begin
    $dumpfile("fa.vcd");
    $dumpvars(0,tb_fa);
  end

endmodule

DAY3_Full_adder/fa.vcd
$date
	Tue Jun 10 16:09:12 2025
$end
$version
	Icarus Verilog
$end
$timescale
	1s
$end
$scope module tb_fa $end
$var wire 1 ! sum $end
$var wire 1 " carry $end
$var reg 1 # a_in $end
$var reg 1 $ b_in $end
$var reg 1 % c_in $end
$scope module uut $end
$var wire 1 # a_in $end
$var wire 1 $ b_in $end
$var wire 1 % c_in $end
$var wire 1 " carry $end
$var wire 1 ! sum $end
$upscope $end
$upscope $end
$enddefinitions $end
$comment Show the parameter values. $end
$dumpall
$end
#0
$dumpvars
0%
0$
0#
0"
0!
$end
#10
1!
1%
#20
0%
1$
#30
1"
0!
1%
#40
0"
1!
0%
0$
1#
#50
1"
0!
1%
#60
0%
1$
#70
1!
1%
